LICENSE
pyrthomas/UNKNOWN.egg-info/PKG-INFO
pyrthomas/UNKNOWN.egg-info/SOURCES.txt
pyrthomas/UNKNOWN.egg-info/dependency_links.txt
pyrthomas/UNKNOWN.egg-info/top_level.txt
pyrthomas/__init__.py
pyrthomas/constants.py
pyrthomas/cytoscape.py
pyrthomas/decorators.py
pyrthomas/models.py
pyrthomas/network.py
pyrthomas/network_analyser.py
pyrthomas/tests.py
pyrthomas/utils.py
pyrthomas-0.0.10.dist-info/LICENSE
pyrthomas-0.0.10.dist-info/WHEEL
pyrthomas-0.0.10.dist-info/METADATA
pyrthomas-0.0.10.dist-info/RECORD
